mcpartools/__init__.py
mcpartools/_version.py
mcpartools/generatemc.py
mcpartools/generator.py
mcpartools/mcengine/__init__.py
mcpartools/mcengine/common.py
mcpartools/mcengine/fluka.py
mcpartools/mcengine/mcengine.py
mcpartools/mcengine/shieldhit.py
mcpartools/mcengine/data/SH12A_ICRU_table.json
mcpartools/mcengine/data/__init__.py
mcpartools/mcengine/data/collect.sh
mcpartools/mcengine/data/run_fluka.sh
mcpartools/mcengine/data/run_shieldhit.sh
mcpartools/scheduler/__init__.py
mcpartools/scheduler/base.py
mcpartools/scheduler/common.py
mcpartools/scheduler/lsf.py
mcpartools/scheduler/slurm.py
mcpartools/scheduler/torque.py
mcpartools/scheduler/data/__init__.py
mcpartools/scheduler/data/run_slurm.sh
mcpartools/scheduler/data/run_torque.sh
mcpartools/scheduler/data/submit_slurm.sh
mcpartools/scheduler/data/submit_torque.sh
mcpartools-0.6.2.dist-info/LICENSE
mcpartools-0.6.2.dist-info/METADATA
mcpartools-0.6.2.dist-info/WHEEL
mcpartools-0.6.2.dist-info/entry_points.txt
mcpartools-0.6.2.dist-info/top_level.txt
mcpartools-0.6.2.dist-info/RECORD
